unity_sds_client/__init__.py
unity_sds_client/envs/environments.cfg
unity_sds_client/resources/__init__.py
unity_sds_client/resources/collection.py
unity_sds_client/resources/data_file.py
unity_sds_client/resources/dataset.py
unity_sds_client/resources/job.py
unity_sds_client/resources/job_status.py
unity_sds_client/resources/process.py
unity_sds_client/resources/stac_collection.py
unity_sds_client/services/__init__.py
unity_sds_client/services/application_service.py
unity_sds_client/services/data_service.py
unity_sds_client/services/health_service.py
unity_sds_client/services/process_service.py
unity_sds_client/unity.py
unity_sds_client/unity_environments.py
unity_sds_client/unity_exception.py
unity_sds_client/unity_services.py
unity_sds_client/unity_session.py
unity_sds_client/utils/__init__.py
unity_sds_client/utils/http.py
unity_sds_client-0.12.0.dist-info/LICENSE
unity_sds_client-0.12.0.dist-info/METADATA
unity_sds_client-0.12.0.dist-info/WHEEL
unity_sds_client-0.12.0.dist-info/RECORD
