Metadata-Version: 2.1
Name: unity-sds-client
Version: 0.12.0
Summary: Unity-Py is a Python client to simplify interactions with NASA's Unity Platform.
Home-page: https://github.com/unity-sds/unity-py
License: Apache-2.0
Author: Anil Natha, Mike Gangl
Requires-Python: >=3.8,<4.0
Classifier: License :: OSI Approved :: Apache Software License
Classifier: Programming Language :: Python :: 3
Classifier: Programming Language :: Python :: 3.8
Classifier: Programming Language :: Python :: 3.9
Classifier: Programming Language :: Python :: 3.10
Classifier: Programming Language :: Python :: 3.11
Classifier: Programming Language :: Python :: 3.12
Requires-Dist: giturlparse (>=0.10.0,<0.11.0)
Requires-Dist: jsonschema (>=4.22.0,<5.0.0)
Requires-Dist: pystac (>=1.7.3,<2.0.0)
Requires-Dist: requests (>=2.28.0,<3.0.0)
Requires-Dist: tenacity (>=8.0.1,<9.0.0)
Requires-Dist: unity-sds-apgs-client (==0.1.0)
Requires-Dist: unity-sps-ogc-processes-api-python-client (>=2.0.1,<3.0.0)
Project-URL: Repository, https://github.com/unity-sds/unity-py
